radula/__init__.py
radula/_version.py
radula/parallel.py
radula/proxy.py
radula/rad.py
radula-0.8.7.dist-info/LICENSE
radula-0.8.7.dist-info/METADATA
radula-0.8.7.dist-info/WHEEL
radula-0.8.7.dist-info/entry_points.txt
radula-0.8.7.dist-info/pbr.json
radula-0.8.7.dist-info/top_level.txt
radula-0.8.7.dist-info/RECORD
