Metadata-Version: 2.1
Name: radula
Version: 0.8.7
Summary: RadosGW client for Ceph S3 storage
Home-page: https://github.com/bibby/radula
Author: bibby
Author-email: andrew.bibby@nantomics.com
License: UNKNOWN
Keywords: ceph radosgw s3
Platform: UNKNOWN
Classifier: Development Status :: 5 - Production/Stable
Classifier: Programming Language :: Python :: 2.7
Classifier: Environment :: Console
Classifier: Intended Audience :: Science/Research
Classifier: License :: OSI Approved :: MIT License
Classifier: Topic :: System :: Filesystems
Classifier: Operating System :: POSIX :: Linux
Requires-Dist: boto
Requires-Dist: filechunkio
